vital_graph-0.0.6.dist-info/licenses/LICENSE
vitalgraph/__init__.py
vitalgraph/admin_cmd/__init__.py
vitalgraph/admin_cmd/vitalgraphdb_admin_cmd.py
vitalgraph/api/__init__.py
vitalgraph/api/vitalgraph_api.py
vitalgraph/api/frontend/dist/android-chrome-192x192.png
vitalgraph/api/frontend/dist/android-chrome-512x512.png
vitalgraph/api/frontend/dist/android-icon-144x144.png
vitalgraph/api/frontend/dist/android-icon-192x192.png
vitalgraph/api/frontend/dist/android-icon-36x36.png
vitalgraph/api/frontend/dist/android-icon-48x48.png
vitalgraph/api/frontend/dist/android-icon-72x72.png
vitalgraph/api/frontend/dist/android-icon-96x96.png
vitalgraph/api/frontend/dist/app.bundle.js
vitalgraph/api/frontend/dist/app.css
vitalgraph/api/frontend/dist/apple-icon-114x114.png
vitalgraph/api/frontend/dist/apple-icon-120x120.png
vitalgraph/api/frontend/dist/apple-icon-144x144.png
vitalgraph/api/frontend/dist/apple-icon-152x152.png
vitalgraph/api/frontend/dist/apple-icon-180x180.png
vitalgraph/api/frontend/dist/apple-icon-57x57.png
vitalgraph/api/frontend/dist/apple-icon-60x60.png
vitalgraph/api/frontend/dist/apple-icon-72x72.png
vitalgraph/api/frontend/dist/apple-icon-76x76.png
vitalgraph/api/frontend/dist/apple-icon-precomposed.png
vitalgraph/api/frontend/dist/apple-icon.png
vitalgraph/api/frontend/dist/apple-touch-icon.png
vitalgraph/api/frontend/dist/browserconfig.xml
vitalgraph/api/frontend/dist/favicon-16x16.png
vitalgraph/api/frontend/dist/favicon-32x32.png
vitalgraph/api/frontend/dist/favicon-96x96.png
vitalgraph/api/frontend/dist/favicon.ico
vitalgraph/api/frontend/dist/figma.svg
vitalgraph/api/frontend/dist/flowbite-react.svg
vitalgraph/api/frontend/dist/flowbite.svg
vitalgraph/api/frontend/dist/index.html
vitalgraph/api/frontend/dist/manifest.json
vitalgraph/api/frontend/dist/ms-icon-144x144.png
vitalgraph/api/frontend/dist/ms-icon-150x150.png
vitalgraph/api/frontend/dist/ms-icon-310x310.png
vitalgraph/api/frontend/dist/ms-icon-70x70.png
vitalgraph/api/frontend/dist/mstile-150x150.png
vital_graph-0.0.6.dist-info/METADATA
vital_graph-0.0.6.dist-info/WHEEL
vital_graph-0.0.6.dist-info/entry_points.txt
vital_graph-0.0.6.dist-info/top_level.txt
vital_graph-0.0.6.dist-info/RECORD
