Metadata-Version: 2.4
Name: vital-graph
Version: 0.0.6
Summary: VitalGraph
Author-email: Marc Hadfield <marc@vital.ai>
License: Apache License 2.0
Project-URL: Homepage, https://github.com/vital-ai/vital-graph
Project-URL: Repository, https://github.com/vital-ai/vital-graph
Project-URL: Documentation, https://github.com/vital-ai/vital-graph/docs
Project-URL: Bug Tracker, https://github.com/vital-ai/vital-graph/issues
Keywords: knowledge-graph,rdf,sparql,database,semantic-web
Classifier: Programming Language :: Python :: 3.12
Classifier: License :: OSI Approved :: Apache Software License
Classifier: Operating System :: OS Independent
Requires-Python: >=3.12
License-File: LICENSE
Requires-Dist: vital-ai-vitalsigns>=0.1.46
Requires-Dist: vital-ai-haley-kg>=0.1.24
Requires-Dist: python-dotenv
Requires-Dist: rdflib>=7.0.0
Requires-Dist: PyLD>=2.0.0
Requires-Dist: six>=1.7.0
Requires-Dist: pyoxigraph>=0.4.11
Requires-Dist: openai>=1.0.0
Requires-Dist: minio>=7.0.0
Provides-Extra: client
Requires-Dist: httpx>=0.27.0; extra == "client"
Requires-Dist: aiohttp>=3.9.0; extra == "client"
Requires-Dist: pydantic>=2.0.0; extra == "client"
Requires-Dist: PyYAML>=6.0; extra == "client"
Requires-Dist: tabulate>=0.9.0; extra == "client"
Requires-Dist: click-repl>=0.3.0; extra == "client"
Requires-Dist: aiofiles>=23.0.0; extra == "client"
Provides-Extra: server
Requires-Dist: fastapi[models,standard]>=0.104.0; extra == "server"
Requires-Dist: uvicorn; extra == "server"
Requires-Dist: SQLAlchemy[asyncio]>=2.0.23; extra == "server"
Requires-Dist: psycopg[binary,pool]>=3.1.13; extra == "server"
Requires-Dist: asyncpg>=0.29.0; extra == "server"
Requires-Dist: alembic>=1.12.0; extra == "server"
Requires-Dist: pgvector>=0.2.4; extra == "server"
Requires-Dist: aiofiles>=23.0.0; extra == "server"
Requires-Dist: Jinja2>=3.1.0; extra == "server"
Requires-Dist: starlette>=0.27.0; extra == "server"
Requires-Dist: itsdangerous>=2.1.0; extra == "server"
Requires-Dist: PyJWT>=2.8.0; extra == "server"
Requires-Dist: email-validator>=2.0.0; extra == "server"
Requires-Dist: click-repl>=0.3.0; extra == "server"
Requires-Dist: tabulate>=0.9.0; extra == "server"
Requires-Dist: pytidb[models]; extra == "server"
Requires-Dist: pytidb; extra == "server"
Requires-Dist: weaviate-client>=4.19.2; extra == "server"
Provides-Extra: dev
Requires-Dist: pytest>=7.0.0; extra == "dev"
Requires-Dist: pytest-asyncio>=0.21.0; extra == "dev"
Requires-Dist: black>=23.0.0; extra == "dev"
Requires-Dist: flake8>=6.0.0; extra == "dev"
Requires-Dist: mypy>=1.5.0; extra == "dev"
Requires-Dist: pre-commit>=3.0.0; extra == "dev"
Provides-Extra: test
Requires-Dist: pytest>=7.0.0; extra == "test"
Requires-Dist: pytest-asyncio>=0.21.0; extra == "test"
Requires-Dist: pytest-cov>=4.0.0; extra == "test"
Provides-Extra: docs
Requires-Dist: sphinx>=7.0.0; extra == "docs"
Requires-Dist: sphinx-rtd-theme>=1.3.0; extra == "docs"
Requires-Dist: myst-parser>=2.0.0; extra == "docs"
Provides-Extra: all
Requires-Dist: vital-graph[client,dev,docs,server,test]; extra == "all"
Dynamic: license-file
